<?xml version="1.0" encoding="iso-8859-1"?>
<Document>
<Chapter>
  <Header>CHAPTER IV</Header>
  <Name>HUMAN RIGHTS</Name>
</Chapter>
<ExternalData>
  <Numsect>3</Numsect>
  <Titlesect>International Covenant on Economic, Social and Cultural Rights</Titlesect>
  <Conclusion>New York, 16 December 1966</Conclusion>
  <EIF>
    <Label>Entry into force</Label>
    <Labeltext>3 January 1976, in accordance with article 27.</Labeltext>
    <Notes>
      <Note>1</Note>
    </Notes>
  </EIF>
</ExternalData>
</Document>
