<Header>CHAPTER XIX</Header>
<Name>COMMODITIES</Name>
<ExternalData>
  <Numsect>15</Numsect>
  <Subnumsect>a</Subnumsect>
  <Subtitlesect>Extension of the International Coffee Agreement, 1976*</Subtitlesect>
  <Conclusion>London, 25 September 1981</Conclusion>
  <EIF>1 October 1982, in accordance with paragraph 2of Resolution No. 318 adopted by the International Coffee Council on 25 September 1981. The Agreement expired in accordance with its provisions on 30 September 1983.</EIF>
</ExternalData>
